{
    "_metadata": {
        "totals": {
            "total_items": 9
        },
        "description": "demons prefix modifiers with stat bonuses/penalties",
        "type": "prefix_modifier",
        "version": "1.0",
        "last_updated": "2025-12-16"
    },
    "items": [
        {
            "rarityWeight": 50,
            "name": "Lesser",
            "traits": {
                "healthMultiplier": {
                    "value": 0.9,
                    "type": "Multiplier"
                },
                "demonAura": {
                    "value": true,
                    "type": "Boolean"
                },
                "fireDamage": {
                    "value": 5,
                    "type": "Flat"
                },
                "resistFire": {
                    "value": 50,
                    "type": "Percentage"
                },
                "resistHoly": {
                    "value": -25,
                    "type": "Percentage"
                },
                "damageMultiplier": {
                    "value": 1.0,
                    "type": "Multiplier"
                }
            },
            "displayName": "Lesser"
        },
        {
            "rarityWeight": 50,
            "name": "Imp",
            "traits": {
                "healthMultiplier": {
                    "value": 0.8,
                    "type": "Multiplier"
                },
                "teleportShort": {
                    "value": true,
                    "type": "Boolean"
                },
                "resistHoly": {
                    "value": -30,
                    "type": "Percentage"
                },
                "evadeChance": {
                    "value": 15,
                    "type": "Percentage"
                },
                "resistFire": {
                    "value": 75,
                    "type": "Percentage"
                },
                "damageMultiplier": {
                    "value": 1.1,
                    "type": "Multiplier"
                },
                "fireDamage": {
                    "value": 8,
                    "type": "Flat"
                }
            },
            "displayName": "Imp"
        },
        {
            "rarityWeight": 50,
            "name": "Corrupted",
            "traits": {
                "healthMultiplier": {
                    "value": 1.0,
                    "type": "Multiplier"
                },
                "corruptionChance": {
                    "value": 15,
                    "type": "Percentage"
                },
                "corruptionDamage": {
                    "value": 10,
                    "type": "Flat"
                },
                "resistHoly": {
                    "value": -20,
                    "type": "Percentage"
                },
                "resistFire": {
                    "value": 40,
                    "type": "Percentage"
                },
                "damageMultiplier": {
                    "value": 1.1,
                    "type": "Multiplier"
                }
            },
            "displayName": "Corrupted"
        },
        {
            "rarityWeight": 30,
            "name": "Fiend",
            "traits": {
                "healthMultiplier": {
                    "value": 1.4,
                    "type": "Multiplier"
                },
                "corruptionAura": {
                    "value": 10,
                    "type": "Percentage"
                },
                "resistHoly": {
                    "value": -35,
                    "type": "Percentage"
                },
                "resistMagic": {
                    "value": 20,
                    "type": "Percentage"
                },
                "fearOnHit": {
                    "value": 15,
                    "type": "Percentage"
                },
                "fireDamage": {
                    "value": 20,
                    "type": "Flat"
                },
                "resistFire": {
                    "value": 60,
                    "type": "Percentage"
                },
                "damageMultiplier": {
                    "value": 1.5,
                    "type": "Multiplier"
                },
                "darkMagic": {
                    "value": 15,
                    "type": "Flat"
                }
            },
            "displayName": "Fiend"
        },
        {
            "rarityWeight": 30,
            "name": "Infernal",
            "traits": {
                "healthMultiplier": {
                    "value": 1.5,
                    "type": "Multiplier"
                },
                "resistHoly": {
                    "value": -40,
                    "type": "Percentage"
                },
                "fireDamage": {
                    "value": 30,
                    "type": "Flat"
                },
                "fireAura": {
                    "value": 15,
                    "type": "Flat"
                },
                "resistFire": {
                    "value": 100,
                    "type": "Percentage"
                },
                "damageMultiplier": {
                    "value": 1.6,
                    "type": "Multiplier"
                },
                "igniteChance": {
                    "value": 25,
                    "type": "Percentage"
                },
                "resistCold": {
                    "value": -50,
                    "type": "Percentage"
                }
            },
            "displayName": "Infernal"
        },
        {
            "rarityWeight": 30,
            "name": "Vile",
            "traits": {
                "healthMultiplier": {
                    "value": 1.3,
                    "type": "Multiplier"
                },
                "diseaseChance": {
                    "value": 30,
                    "type": "Percentage"
                },
                "corruptionDamage": {
                    "value": 20,
                    "type": "Flat"
                },
                "resistPoison": {
                    "value": 75,
                    "type": "Percentage"
                },
                "resistFire": {
                    "value": 50,
                    "type": "Percentage"
                },
                "corruptionAura": {
                    "value": 15,
                    "type": "Percentage"
                },
                "poisonDamage": {
                    "value": 15,
                    "type": "Flat"
                },
                "damageMultiplier": {
                    "value": 1.4,
                    "type": "Multiplier"
                },
                "resistHoly": {
                    "value": -45,
                    "type": "Percentage"
                }
            },
            "displayName": "Vile"
        },
        {
            "rarityWeight": 15,
            "name": "Greater",
            "traits": {
                "healthMultiplier": {
                    "value": 2.0,
                    "type": "Multiplier"
                },
                "corruptionAura": {
                    "value": 20,
                    "type": "Percentage"
                },
                "resistHoly": {
                    "value": -50,
                    "type": "Percentage"
                },
                "teleport": {
                    "value": true,
                    "type": "Boolean"
                },
                "resistMagic": {
                    "value": 35,
                    "type": "Percentage"
                },
                "fireDamage": {
                    "value": 40,
                    "type": "Flat"
                },
                "fearAura": {
                    "value": 20,
                    "type": "Percentage"
                },
                "resistFire": {
                    "value": 75,
                    "type": "Percentage"
                },
                "summonDemons": {
                    "value": 2,
                    "type": "Flat"
                },
                "damageMultiplier": {
                    "value": 2.0,
                    "type": "Multiplier"
                },
                "darkMagic": {
                    "value": 35,
                    "type": "Flat"
                }
            },
            "displayName": "Greater"
        },
        {
            "rarityWeight": 15,
            "name": "Hellborn",
            "traits": {
                "healthMultiplier": {
                    "value": 2.2,
                    "type": "Multiplier"
                },
                "hellfireDamage": {
                    "value": 40,
                    "type": "Flat"
                },
                "resistHoly": {
                    "value": -60,
                    "type": "Percentage"
                },
                "resistPhysical": {
                    "value": 25,
                    "type": "Percentage"
                },
                "fireDamage": {
                    "value": 50,
                    "type": "Flat"
                },
                "lifeSteal": {
                    "value": 15,
                    "type": "Percentage"
                },
                "fireAura": {
                    "value": 25,
                    "type": "Flat"
                },
                "resistFire": {
                    "value": 100,
                    "type": "Percentage"
                },
                "damageMultiplier": {
                    "value": 2.1,
                    "type": "Multiplier"
                },
                "resistCold": {
                    "value": -75,
                    "type": "Percentage"
                },
                "hellfire": {
                    "value": true,
                    "type": "Boolean"
                }
            },
            "displayName": "Hellborn"
        },
        {
            "rarityWeight": 15,
            "name": "Shadow",
            "traits": {
                "healthMultiplier": {
                    "value": 1.8,
                    "type": "Multiplier"
                },
                "teleport": {
                    "value": true,
                    "type": "Boolean"
                },
                "resistMagic": {
                    "value": 40,
                    "type": "Percentage"
                },
                "shadowDamage": {
                    "value": 35,
                    "type": "Flat"
                },
                "evadeChance": {
                    "value": 30,
                    "type": "Percentage"
                },
                "criticalChance": {
                    "value": 25,
                    "type": "Percentage"
                },
                "stealth": {
                    "value": 40,
                    "type": "Flat"
                },
                "resistHoly": {
                    "value": -55,
                    "type": "Percentage"
                },
                "damageMultiplier": {
                    "value": 2.2,
                    "type": "Multiplier"
                },
                "darkMagic": {
                    "value": 45,
                    "type": "Flat"
                }
            },
            "displayName": "Shadow"
        }
    ],
    "notes": {
        "usage": "Stat modifiers applied BEFORE base name. Used at runtime based on item rarity. Not used in pattern generation."
    }
}