{
  "metadata": {
    "description": "Wood material properties for crafting system - stat bonuses applied to weapons",
    "version": "5.1",
    "lastUpdated": "2026-01-10",
    "type": "materials_properties_catalog",
    "totalMaterials": 9,
    "usage": "Material properties define stat bonuses based on item type. itemTypeTraits apply bonuses primarily to weapons (bows, staves).",
    "notes": [
      "Wood materials focus on weapon bonuses with wisdom/intelligence benefits",
      "Runtime: Pick material by rarityWeight → Apply shared + itemTypeTraits[itemType] → Calculate final stats"
    ]
  },
  "items": [
    {
      "slug": "oak",
      "budgetCost": 2,
      "name": "Oak",
      "attributes": {
        "dexterity": 10,
        "intelligence": 8,
        "charisma": 8,
        "strength": 10,
        "constitution": 10,
        "wisdom": 8
      },
      "traits": {
        "durability": 70,
        "weight": 1.0,
        "strength": 60,
        "flexibility": 40
      },
      "displayName": "Oak",
      "itemTypeTraits": {
        "weapon": {
          "damage": 0,
          "value": 3
        }
      },
      "rarityWeight": 60,
      "rarity": 60
    },
    {
      "slug": "ash",
      "budgetCost": 3,
      "name": "Ash",
      "attributes": {
        "dexterity": 10,
        "intelligence": 8,
        "charisma": 8,
        "strength": 10,
        "constitution": 10,
        "wisdom": 8
      },
      "traits": {
        "durability": 75,
        "weight": 0.9,
        "strength": 70,
        "flexibility": 60
      },
      "displayName": "Ash",
      "itemTypeTraits": {
        "weapon": {
          "damage": 1,
          "shockAbsorption": 20,
          "value": 8
        }
      },
      "rarityWeight": 50,
      "rarity": 50
    },
    {
      "slug": "maple",
      "budgetCost": 4,
      "name": "Maple",
      "attributes": {
        "dexterity": 10,
        "intelligence": 8,
        "charisma": 8,
        "strength": 10,
        "constitution": 10,
        "wisdom": 8
      },
      "traits": {
        "durability": 72,
        "weight": 0.85,
        "strength": 65,
        "flexibility": 70
      },
      "displayName": "Maple",
      "itemTypeTraits": {
        "weapon": {
          "damage": 1,
          "enchantability": 60,
          "naturalResonance": 25,
          "value": 12
        }
      },
      "rarityWeight": 42,
      "rarity": 42
    },
    {
      "slug": "yew",
      "budgetCost": 7,
      "name": "Yew",
      "attributes": {
        "dexterity": 10,
        "intelligence": 8,
        "charisma": 8,
        "strength": 10,
        "constitution": 10,
        "wisdom": 8
      },
      "traits": {
        "durability": 80,
        "weight": 0.8,
        "strength": 75,
        "flexibility": 80
      },
      "displayName": "Yew",
      "itemTypeTraits": {
        "weapon": {
          "damage": 2,
          "rangeBonus": 15,
          "critChance": 3,
          "poisonDamage": 5,
          "value": 30
        }
      },
      "rarityWeight": 30,
      "rarity": 30
    },
    {
      "slug": "ebony",
      "budgetCost": 18,
      "name": "Ebony",
      "attributes": {
        "dexterity": 10,
        "intelligence": 8,
        "charisma": 8,
        "strength": 10,
        "constitution": 10,
        "wisdom": 8
      },
      "traits": {
        "durability": 100,
        "weight": 1.2,
        "strength": 85,
        "flexibility": 45,
        "visualColor": "black"
      },
      "displayName": "Ebony",
      "itemTypeTraits": {
        "weapon": {
          "damage": 6,
          "bonusShadowDamage": 25,
          "magicAbsorption": 20,
          "intelligenceBonus": 2,
          "value": 120
        }
      },
      "rarityWeight": 10,
      "rarity": 10
    },
    {
      "slug": "ironwood",
      "budgetCost": 15,
      "name": "Ironwood",
      "attributes": {
        "dexterity": 10,
        "intelligence": 8,
        "charisma": 8,
        "strength": 10,
        "constitution": 10,
        "wisdom": 8
      },
      "traits": {
        "durability": 120,
        "weight": 1.3,
        "strength": 95,
        "flexibility": 30
      },
      "displayName": "Ironwood",
      "itemTypeTraits": {
        "weapon": {
          "damage": 5,
          "armorPenetration": 10,
          "strengthBonus": 1,
          "value": 100
        }
      },
      "rarityWeight": 12,
      "rarity": 12
    },
    {
      "slug": "living-wood",
      "budgetCost": 22,
      "name": "Living Wood",
      "attributes": {
        "dexterity": 10,
        "intelligence": 8,
        "charisma": 8,
        "strength": 10,
        "constitution": 10,
        "wisdom": 8
      },
      "traits": {
        "durability": 90,
        "weight": 0.7,
        "strength": 80,
        "flexibility": 75,
        "selfRepair": true
      },
      "displayName": "Living Wood",
      "itemTypeTraits": {
        "weapon": {
          "damage": 4,
          "bonusNatureDamage": 35,
          "healthRegen": 5,
          "wisdomBonus": 2,
          "value": 180
        }
      },
      "rarityWeight": 8,
      "rarity": 8
    },
    {
      "slug": "elder-wood",
      "budgetCost": 27,
      "name": "Elder Wood",
      "attributes": {
        "dexterity": 10,
        "intelligence": 8,
        "charisma": 8,
        "strength": 10,
        "constitution": 10,
        "wisdom": 8
      },
      "traits": {
        "durability": 110,
        "weight": 0.6,
        "strength": 90,
        "flexibility": 85,
        "timeless": true
      },
      "displayName": "Elder Wood",
      "itemTypeTraits": {
        "weapon": {
          "damage": 7,
          "bonusAncientPower": 40,
          "wisdomBonus": 4,
          "intelligenceBonus": 2,
          "value": 250
        }
      },
      "rarityWeight": 5,
      "rarity": 5
    },
    {
      "slug": "heartwood",
      "budgetCost": 34,
      "name": "Heartwood",
      "attributes": {
        "dexterity": 10,
        "intelligence": 8,
        "charisma": 8,
        "strength": 10,
        "constitution": 10,
        "wisdom": 8
      },
      "traits": {
        "durability": 130,
        "weight": 0.5,
        "strength": 100,
        "flexibility": 90,
        "legendary": true
      },
      "displayName": "Heartwood",
      "itemTypeTraits": {
        "weapon": {
          "damage": 9,
          "bonusSpiritDamage": 45,
          "lifeBond": 50,
          "allStatsBonus": 2,
          "value": 350
        }
      },
      "rarityWeight": 4,
      "rarity": 4
    }
  ]
}
